{"errors":[],"warnings":[],"namedChunkGroups":{"app":{"chunks":[4,3,2],"assets":["webpack-runtime-7c3d025e77966fdb09a5.js","webpack-runtime-7c3d025e77966fdb09a5.js.map","framework-43898561dafbdf32aefd.js","framework-43898561dafbdf32aefd.js.map","app-047aef968ebb7566b414.js","app-047aef968ebb7566b414.js.map"],"children":{},"childAssets":{}},"component---src-templates-docs-js":{"chunks":[],"assets":[],"children":{},"childAssets":{}}},"assetsByChunkName":{"app":["webpack-runtime-7c3d025e77966fdb09a5.js","framework-43898561dafbdf32aefd.js","app-047aef968ebb7566b414.js"],"component---src-templates-docs-js":[]}}